agentclpr/__init__.py
agentclpr/infer/__init__.py
agentclpr/infer/detector.py
agentclpr/infer/server.py
agentclpr/infer/system.py
agentclpr/infer/utility.py
agentclpr/resources/char_dicts/clp_dict.txt
agentclpr/resources/pretrained_models/ch_mul_m_cls.onnx
agentclpr/resources/pretrained_models/ch_mul_v2_c_det.onnx
agentclpr/resources/pretrained_models/clp_det.onnx
agentclpr/resources/pretrained_models/clp_v2_c_rec.onnx
agentclpr-1.1.0.dist-info/LICENSE
agentclpr-1.1.0.dist-info/METADATA
agentclpr-1.1.0.dist-info/WHEEL
agentclpr-1.1.0.dist-info/entry_points.txt
agentclpr-1.1.0.dist-info/top_level.txt
agentclpr-1.1.0.dist-info/RECORD
