Metadata-Version: 2.1
Name: agentclpr
Version: 1.1.0
Summary: An easy-to-use Chinese license plate recognition system.
Home-page: https://github.com/AgentMaker/AgentCLPR
Author: jm12138
License: Apache License 2.0
Platform: UNKNOWN
Requires-Dist: agentocr
